andspace_jwt_auth-1.2.7.dist-info/licenses/LICENSE
jwt_auth/__init__.py
jwt_auth/examples.py
jwt_auth/setup.py
jwt_auth/adapters/__init__.py
jwt_auth/adapters/fastapi.py
jwt_auth/core/__init__.py
jwt_auth/core/base.py
jwt_auth/core/config.py
jwt_auth/core/errors.py
jwt_auth/core/user.py
jwt_auth/providers/__init__.py
jwt_auth/providers/casdoor.py
jwt_auth/providers/jwt_provider.py
andspace_jwt_auth-1.2.7.dist-info/METADATA
andspace_jwt_auth-1.2.7.dist-info/WHEEL
andspace_jwt_auth-1.2.7.dist-info/top_level.txt
andspace_jwt_auth-1.2.7.dist-info/RECORD
