Metadata-Version: 2.4
Name: andspace-jwt-auth
Version: 1.2.7
Summary: Framework-agnostic JWT token validation library
Home-page: https://github.com/andspace/jwt-auth
Author: And
Author-email: And <and.webdev@gmail.com>
License: MIT
Project-URL: Homepage, https://github.com/andspace/jwt-auth
Project-URL: Repository, https://github.com/andspace/jwt-auth
Project-URL: Documentation, https://github.com/andspace/jwt-auth#readme
Project-URL: Bug Tracker, https://github.com/andspace/jwt-auth/issues
Keywords: jwt,authentication,token,validation,casdoor,fastapi
Classifier: Development Status :: 4 - Beta
Classifier: Intended Audience :: Developers
Classifier: License :: OSI Approved :: MIT License
Classifier: Operating System :: OS Independent
Classifier: Programming Language :: Python :: 3
Classifier: Programming Language :: Python :: 3.8
Classifier: Programming Language :: Python :: 3.9
Classifier: Programming Language :: Python :: 3.10
Classifier: Programming Language :: Python :: 3.11
Classifier: Topic :: Internet :: WWW/HTTP
Classifier: Topic :: Security
Classifier: Topic :: Software Development :: Libraries :: Python Modules
Requires-Python: >=3.8
License-File: LICENSE
Requires-Dist: PyJWT[crypto]>=2.4.0
Requires-Dist: cryptography>=3.4.0
Requires-Dist: casdoor>=1.0.0
Provides-Extra: casdoor
Requires-Dist: casdoor>=1.0.0; extra == "casdoor"
Provides-Extra: fastapi
Requires-Dist: fastapi>=0.68.0; extra == "fastapi"
Provides-Extra: dev
Requires-Dist: pytest>=7.0.0; extra == "dev"
Requires-Dist: pytest-asyncio>=0.20.0; extra == "dev"
Requires-Dist: pytest-cov>=4.0.0; extra == "dev"
Requires-Dist: black>=22.0.0; extra == "dev"
Requires-Dist: flake8>=4.0.0; extra == "dev"
Requires-Dist: mypy>=0.991; extra == "dev"
Requires-Dist: isort>=5.10.0; extra == "dev"
Provides-Extra: all
Requires-Dist: casdoor>=1.0.0; extra == "all"
Requires-Dist: fastapi>=0.68.0; extra == "all"
Dynamic: author
Dynamic: home-page
Dynamic: license-file
Dynamic: requires-python
